[
    {
        "title": "Gangnam Style",
        "artist": "PSY",
        "videoId": "9bZkp7q19f0",
        "location": {
            "lat": 37.5665,
            "lng": 126.9780
        }
    },
    {
        "title": "Shape of You",
        "artist": "Ed Sheeran",
        "videoId": "JGwWNGJdvx8",
        "location": {
            "lat": 52.2053,
            "lng": 0.1218
        }
    },
    {
        "title": "Ai Se Eu Te Pego",
        "artist": "Michel Teló",
        "videoId": "hcm55lU9knw",
        "location": {
            "lat": -23.5505,
            "lng": -46.6333
        }
    },
    {
        "title": "Hips Don't Lie",
        "artist": "Shakira",
        "videoId": "DUT5rEU6pqM",
        "location": {
            "lat": 4.7110,
            "lng": -74.0721
        }
    },
    {
        "title": "Jai Ho",
        "artist": "A. R. Rahman",
        "videoId": "Yc5OyXmHD0w",
        "location": {
            "lat": 19.0760,
            "lng": 72.8777
        }
    },
    {
        "title": "Rolling in the Deep",
        "artist": "Adele",
        "videoId": "rYEDA3JcQqw",
        "location": {
            "lat": 51.5074,
            "lng": -0.1278
        }
    },
    {
        "title": "Waka Waka (This Time for Africa)",
        "artist": "Shakira",
        "videoId": "pRpeEdMmmQ0",
        "location": {
            "lat": 1.2921,
            "lng": 36.8219
        }
    },
    {
        "title": "Take Me Home, Country Roads",
        "artist": "John Denver",
        "videoId": "1vrEljMfXYo",
        "location": {
            "lat": 39.0000,
            "lng": -80.0000
        }
    },
    {
        "title": "Con Calma",
        "artist": "Daddy Yankee",
        "videoId": "DiItGE3eAyQ",
        "location": {
            "lat": 18.4655,
            "lng": -66.1057
        }
    },
    {
        "title": "Sakura",
        "artist": "Ikimono Gakari",
        "videoId": "Oe0fGXzKb28",
        "location": {
            "lat": 35.6895,
            "lng": 139.6917
        }
    },
    {
        "title": "The Sound of Silence",
        "artist": "Simon & Garfunkel",
        "videoId": "4zLfCnGVeL4",
        "location": {
            "lat": 40.7128,
            "lng": -74.0060
        }
    },
    {
        "title": "Zum Zum",
        "artist": "Daddy Yankee",
        "videoId": "j0k7gzxkS3Y",
        "location": {
            "lat": 40.7306,
            "lng": -73.9866
        }
    },
    {
        "title": "Alf Leila Wa Leila",
        "artist": "Umm Kulthum",
        "videoId": "LJ9X6fy8j90",
        "location": {
            "lat": 30.0444,
            "lng": 31.2357
        }
    },
    {
        "title": "Amor Eterno",
        "artist": "Rocio Durcal",
        "videoId": "Tx-xGV3i0sQ",
        "location": {
            "lat": 19.4326,
            "lng": -99.1332
        }
    },
    {
        "title": "Bohemian Rhapsody",
        "artist": "Queen",
        "videoId": "fJ9rUzIMcZQ",
        "location": {
            "lat": 51.5074,
            "lng": -0.1278
        }
    },
    {
        "title": "Never Gonna Give You Up",
        "artist": "Rick Astley",
        "videoId": "dQw4w9WgXcQ",
        "location": {
            "lat": 51.5085,
            "lng": -0.1257
        }
    }
]